dbmanager/ThothDbManager.py
dbmanager/__init__.py
dbmanager/helpers/__init__.py
dbmanager/helpers/multi_db_generator.py
dbmanager/helpers/preprocess_values.py
dbmanager/helpers/schema.py
dbmanager/helpers/search.py
dbmanager/impl/ThothPgManager.py
dbmanager/impl/ThothSqliteManager.py
dbmanager/impl/__init__.py
thoth_sqldb-0.3.13.dist-info/licenses/LICENSE
thoth_sqldb-0.3.13.dist-info/METADATA
thoth_sqldb-0.3.13.dist-info/WHEEL
thoth_sqldb-0.3.13.dist-info/top_level.txt
thoth_sqldb-0.3.13.dist-info/RECORD
